sogou_scraper_pw/__init__.py
sogou_scraper_pw/sogou_tr.py
sogou_scraper_pw-0.1.0a1.dist-info/WHEEL
sogou_scraper_pw-0.1.0a1.dist-info/METADATA
sogou_scraper_pw-0.1.0a1.dist-info/RECORD
