Metadata-Version: 2.1
Name: sogou-scraper-pw
Version: 0.1.0a1
Summary: 
Home-page: https://github.com/ffreemt/sogou-scraper-playwright
Author: freemt
Requires-Python: >=3.7,<4.0
Classifier: Programming Language :: Python :: 3
Classifier: Programming Language :: Python :: 3.7
Classifier: Programming Language :: Python :: 3.8
Classifier: Programming Language :: Python :: 3.9
Classifier: Programming Language :: Python :: 3.10
Requires-Dist: about-time (>=4.1.0,<5.0.0)
Requires-Dist: get-pwbrowser-sync (>=0.1.0-alpha.3,<0.1.0)
Requires-Dist: logzero (>=1.7.0,<2.0.0)
Requires-Dist: playwright[chromium] (>=1.24.0,<2.0.0)
Requires-Dist: pyquery (>=1.4.3,<2.0.0)
Project-URL: Repository, https://github.com/ffreemt/sogou-scraper-playwright
